{"question_id": "1cea1afa", "question_type": "knowledge-update", "question": "How many Instagram followers do I currently have?", "gold_answer": "600", "n_sessions": 49, "n_evidence_sessions": 2, "runs": [{"model": "ibm-granite/granite-4.1-8b", "variant": "raw", "response_text": "I do not have real-time access to your personal information, including your current number of Instagram followers. To find out how many followers you have, you can simply log into your Instagram account and check your profile page, where the number of followers is displayed prominently.", "input_tokens": 111798, "output_tokens": 53, "latency_ms": 30589, "error": null, "score": 0.0, "context_len_chars": 499151}, {"model": "ibm-granite/granite-4.1-8b", "variant": "state", "response_text": "Based on the provided conversation history, you currently have 600 Instagram followers. This was mentioned in the last exchange where you congratulated yourself on reaching that milestone.", "input_tokens": 7054, "output_tokens": 33, "latency_ms": 693, "error": null, "score": 1.0, "context_len_chars": 31679}, {"model": "ibm-granite/granite-4.0-h-micro", "variant": "raw", "response_text": "You currently have 600 followers on Instagram.", "input_tokens": 106377, "output_tokens": 10, "latency_ms": 21672, "error": null, "score": 1.0, "context_len_chars": 499151}, {"model": "ibm-granite/granite-4.0-h-micro", "variant": "state", "response_text": "You currently have 600 Instagram followers.", "input_tokens": 6679, "output_tokens": 9, "latency_ms": 1488, "error": null, "score": 1.0, "context_len_chars": 31679}]}
