{
  "trajectory_id": "adv03_phase_iv_without_two_consecutive_low_en",
  "domain": "_adversarial",
  "seed": "Probe: low ENI events separated by a single genuine spike — Phase IV requires consecutive low.",
  "persona": "_probe",
  "steps": [
    {"loop_index": 0, "focus_claim_id": "C001", "operator": "T3", "novel_claims": 11, "dup_rate": 0.05, "failure_mode": null, "claims": [{"id":"C001","subject":"x","predicate":"p","object":"y","history":[]}]},
    {"loop_index": 1, "focus_claim_id": "C001", "operator": "T4", "novel_claims": 2, "dup_rate": 0.35, "failure_mode": null, "claims": []},
    {"loop_index": 2, "focus_claim_id": "C001", "operator": "T5", "novel_claims": 1, "dup_rate": 0.55, "failure_mode": null, "claims": []},
    {"loop_index": 3, "focus_claim_id": "C001", "operator": "T5", "novel_claims": 4, "dup_rate": 0.20, "failure_mode": null, "claims": []},
    {"loop_index": 4, "focus_claim_id": "C001", "operator": "T8", "novel_claims": 1, "dup_rate": 0.50, "failure_mode": null, "claims": []},
    {"loop_index": 5, "focus_claim_id": "C001", "operator": "T8", "novel_claims": 0, "dup_rate": 0.65, "failure_mode": "ATTRACTOR_LOCK", "claims": []}
  ],
  "en_events": [
    {"loop_index": 2, "persona": "_probe", "eni_novelty": 0.05, "eni_non_drift": 0.40, "eni_admissibility": 0.0, "eni_composite": 0.15, "admitted": false, "rejection_reason": "alexandria_gate", "novelty_produced_next_loop": 0, "dup_rate_before": 0.35, "dup_rate_after": 0.55},
    {"loop_index": 3, "persona": "_probe", "eni_novelty": 0.20, "eni_non_drift": 0.70, "eni_admissibility": 1.0, "eni_composite": 0.51, "admitted": true, "novelty_produced_next_loop": 4, "dup_rate_before": 0.55, "dup_rate_after": 0.20},
    {"loop_index": 5, "persona": "_probe", "eni_novelty": 0.04, "eni_non_drift": 0.30, "eni_admissibility": 0.0, "eni_composite": 0.11, "admitted": false, "rejection_reason": "alexandria_gate", "novelty_produced_next_loop": 0, "dup_rate_before": 0.50, "dup_rate_after": 0.65}
  ],
  "terminal_failure_mode": "ATTRACTOR_LOCK"
}
